appstrings.py
appstrings-1.0.2.dist-info/LICENSE
appstrings-1.0.2.dist-info/METADATA
appstrings-1.0.2.dist-info/WHEEL
appstrings-1.0.2.dist-info/top_level.txt
appstrings-1.0.2.dist-info/RECORD
