Metadata-Version: 2.1
Name: appstrings
Version: 1.0.2
Summary: Minimal string translation library
Author: Ángel Fernández Pineda
License: EUROPEAN UNION PUBLIC LICENCE v. 1.2
Project-URL: Homepage, https://github.com/afpineda/appstrings-python
Keywords: translation,internationalization,I18N
Classifier: Programming Language :: Python :: 3.11
Classifier: Intended Audience :: Developers
Classifier: Operating System :: OS Independent
Classifier: Topic :: Software Development :: Internationalization
Classifier: License :: OSI Approved :: European Union Public Licence 1.2 (EUPL 1.2)
Requires-Python: >=3.11
License-File: LICENSE
